keras_pipeline/__init__.py
keras_pipeline/callbacks/__init__.py
keras_pipeline/callbacks/history.py
keras_pipeline/callbacks/metrics.py
keras_pipeline/callbacks/printer.py
keras_pipeline/callbacks/progressbar.py
keras_pipeline/callbacks/remote.py
keras_pipeline/callbacks/stopper.py
keras_pipeline/callbacks/utils.py
keras_pipeline/callbacks/valider.py
keras_pipeline/debug/__init__.py
keras_pipeline/debug/type_checker.py
keras_pipeline/files/__init__.py
keras_pipeline/files/manager.py
keras_pipeline/files/image/__init__.py
keras_pipeline/files/image/augmentation.py
keras_pipeline/files/image/loader.py
keras_pipeline/files/image/preprocess.py
keras_pipeline/metrics/__init__.py
keras_pipeline/metrics/metrics.py
keras_pipeline/metrics/utils.py
keras_pipeline/models/__init__.py
keras_pipeline/models/cnn.py
keras_pipeline/monitoring/__init__.py
keras_pipeline/monitoring/logger.py
keras_pipeline/utils/__init__.py
keras_pipeline/utils/batch.py
keras_pipeline/utils/histogram.py
keras_pipeline/utils/utils.py
keras_pipeline-1.0.2.dist-info/LICENSE
keras_pipeline-1.0.2.dist-info/METADATA
keras_pipeline-1.0.2.dist-info/WHEEL
keras_pipeline-1.0.2.dist-info/top_level.txt
keras_pipeline-1.0.2.dist-info/RECORD
