Metadata-Version: 2.1
Name: keras-pipeline
Version: 1.0.2
Summary: Keras/Tensorflow Pipeline
Home-page: https://github.com/egipcy/Pipeline
Author: Amaury Moulin
Author-email: egipcy@gmail.com
License: UNKNOWN
Platform: UNKNOWN
Classifier: Programming Language :: Python :: 3
Classifier: License :: OSI Approved :: GNU General Public License v3 (GPLv3)
Classifier: Operating System :: OS Independent
Requires-Python: >=3.6.10
